README.md
setup.py
VintedPyInterface/__init__.py
VintedPyInterface.egg-info/PKG-INFO
VintedPyInterface.egg-info/SOURCES.txt
VintedPyInterface.egg-info/dependency_links.txt
VintedPyInterface.egg-info/requires.txt
VintedPyInterface.egg-info/top_level.txt