Metadata-Version: 2.1
Name: VintedPyInterface
Version: 0.1.0
Summary: Interface for Vinted front end
Home-page: https://github.com/ProfesseurIssou/VintedPyInterface
Author: Alix Hamidou
Author-email: alix.hamidou@gmail.com
License: MIT
Classifier: Development Status :: 4 - Beta
Classifier: Intended Audience :: Developers
Classifier: License :: OSI Approved :: MIT License
Classifier: Operating System :: Microsoft :: Windows
Classifier: Operating System :: Unix
Classifier: Programming Language :: Python :: 3
Classifier: Topic :: Software Development :: Libraries :: Python Modules
